AUTHORS.rst
CONTRIBUTING.rst
HISTORY.rst
LICENSE
MANIFEST.in
README.rst
setup.cfg
setup.py
opsdroid_skype/__init__.py
opsdroid_skype/connector.py
opsdroid_skype.egg-info/PKG-INFO
opsdroid_skype.egg-info/SOURCES.txt
opsdroid_skype.egg-info/dependency_links.txt
opsdroid_skype.egg-info/entry_points.txt
opsdroid_skype.egg-info/not-zip-safe
opsdroid_skype.egg-info/requires.txt
opsdroid_skype.egg-info/top_level.txt
tests/bot.bot
tests/test_connector.py