Metadata-Version: 1.1
Name: opsdroid-skype
Version: 0.1.0
Summary: Skype support for opsdroid
Home-page: https://github.com/koodaamo/opsdroid-skype
Author: Petri Savolainen
Author-email: petri@koodaamo.fi
License: Apache Software License 2.0
Keywords: opsdroid skype bot
Platform: UNKNOWN
Classifier: Development Status :: 3 - Alpha
Classifier: Intended Audience :: Developers
Classifier: License :: OSI Approved :: Apache Software License
Classifier: Natural Language :: English
Classifier: Programming Language :: Python :: 3
Classifier: Programming Language :: Python :: 3.5
Classifier: Programming Language :: Python :: 3.6
Classifier: Programming Language :: Python :: 3.7
